youtube_downloader/VERSION
youtube_downloader/__init__.py
youtube_downloader/__main__.py
youtube_downloader/cli.py
youtube_downloader/helpers/BulkAudioDownload.py
youtube_downloader/helpers/BulkVideoDownload.py
youtube_downloader/helpers/DownloadAudio.py
youtube_downloader/helpers/DownloadVideo.py
youtube_downloader/helpers/DownloadVideoWithCaption.py
youtube_downloader/helpers/__init__.py
youtube_downloader/helpers/util.py
youtube_downloader/README
youtube_downloader_cli-0.3.1.dist-info/METADATA
youtube_downloader_cli-0.3.1.dist-info/WHEEL
youtube_downloader_cli-0.3.1.dist-info/entry_points.txt
youtube_downloader_cli-0.3.1.dist-info/licenses/LICENSE
youtube_downloader_cli-0.3.1.dist-info/RECORD
