Metadata-Version: 2.4
Name: youtube-downloader-cli
Version: 0.3.1
Summary: CLI tool for download from YouTube
Project-URL: Home, https://github.com/duong-dt/youtube-downloader
Author-email: duong <dotungduong2@gmail.com>
License: This is free and unencumbered software released into the public domain.
License-File: LICENSE
Classifier: Environment :: Console
Classifier: License :: OSI Approved :: The Unlicense (Unlicense)
Classifier: Operating System :: POSIX :: Linux
Requires-Python: >=3.10
Requires-Dist: click<9,>=8.1.8
Requires-Dist: prompt-toolkit<3.0.52
Requires-Dist: pyperclip==1.9.0
Requires-Dist: pytubefix>=8.12
Requires-Dist: questionary==2.1.0
Requires-Dist: rich<14,>=13.9
Provides-Extra: dev
Requires-Dist: ruff>=0.9.2; extra == 'dev'
